nationalmhfilter/__init__.py
nationalmhfilter/main_module.py
nationalmhfilter/records_clean.csv
nationalmhfilter-0.2.0.dist-info/LICENSE
nationalmhfilter-0.2.0.dist-info/METADATA
nationalmhfilter-0.2.0.dist-info/WHEEL
nationalmhfilter-0.2.0.dist-info/RECORD
