Metadata-Version: 2.1
Name: nationalmhfilter
Version: 0.2.0
Summary: The package showcases mental heanlth care records of different social groups and the statistics of each state in the United States, providing evidence and future directions to improve healthcare services.
License: MIT
Author: Fanxi Wang
Requires-Python: >=3.11,<4.0
Classifier: License :: OSI Approved :: MIT License
Classifier: Programming Language :: Python :: 3
Classifier: Programming Language :: Python :: 3.11
Requires-Dist: pandas (>=2.1.4,<4.0.0)
Requires-Dist: requests (>=2.31.0,<3.0.0)
